README.rst
setup.py
doit_py.egg-info/PKG-INFO
doit_py.egg-info/SOURCES.txt
doit_py.egg-info/dependency_links.txt
doit_py.egg-info/requires.txt
doit_py.egg-info/top_level.txt
doitpy/__init__.py
doitpy/coverage.py
doitpy/docs.py
doitpy/package.py
doitpy/pyflakes.py