Metadata-Version: 1.1
Name: doit-py
Version: 0.5.0
Summary: doit tasks for python stuff
Home-page: http://pythonhosted.org/doit-py
Author: Eduardo Naufel Schettino
Author-email: schettino72@gmail.com
License: MIT
Keywords: doit
Platform: any
Classifier: Development Status :: 4 - Beta
Classifier: Intended Audience :: Developers
Classifier: License :: OSI Approved :: MIT License
Classifier: Natural Language :: English
Classifier: Operating System :: OS Independent
Classifier: Programming Language :: Python
Classifier: Programming Language :: Python :: 3
Classifier: Programming Language :: Python :: 3.5
Classifier: Programming Language :: Python :: 3.6
Classifier: Programming Language :: Python :: 3.7
Classifier: Programming Language :: Python :: 3.8
Classifier: Topic :: Software Development :: Libraries
